README.rst
setup.py
detect_sharpWaveRipples/__init__.py
detect_sharpWaveRipples/core.py
detect_sharpWaveRipples.egg-info/PKG-INFO
detect_sharpWaveRipples.egg-info/SOURCES.txt
detect_sharpWaveRipples.egg-info/dependency_links.txt
detect_sharpWaveRipples.egg-info/top_level.txt