Metadata-Version: 1.1
Name: detect-sharpWaveRipples
Version: 0.1.0
Summary: detect sharp wave ripple events from electrophysiological data
Home-page: https://github.com/droumis/detect_sharpWaveRipples
Author: Demetris Roumis
Author-email: roumis.d+package@gmail.com
License: MIT
Platform: UNKNOWN
Classifier: Development Status :: 2 - Pre-Alpha
Classifier: License :: OSI Approved :: MIT License
Classifier: Programming Language :: Python
Classifier: Programming Language :: Python :: 2
Classifier: Programming Language :: Python :: 2.7
Classifier: Programming Language :: Python :: 3
Classifier: Programming Language :: Python :: 3.4
Classifier: Programming Language :: Python :: 3.5
Classifier: Programming Language :: Python :: 3.6
Classifier: Programming Language :: Python :: 3.7
